oneaccount/__init__.py
oneaccount/main.py
oneaccount-1.0.1.dist-info/LICENSE.txt
oneaccount-1.0.1.dist-info/METADATA
oneaccount-1.0.1.dist-info/WHEEL
oneaccount-1.0.1.dist-info/top_level.txt
oneaccount-1.0.1.dist-info/RECORD
